django_datadog_logger/__init__.py
django_datadog_logger/celery.py
django_datadog_logger/encoders.py
django_datadog_logger/local.py
django_datadog_logger/recursion.py
django_datadog_logger/wsgi.py
django_datadog_logger/formatters/__init__.py
django_datadog_logger/formatters/datadog.py
django_datadog_logger/middleware/__init__.py
django_datadog_logger/middleware/error_log.py
django_datadog_logger/middleware/request_id.py
django_datadog_logger/middleware/request_log.py
django_datadog_logger/rest_framework/__init__.py
django_datadog_logger/rest_framework/mixins.py
django_datadog_logger-0.7.3.dist-info/AUTHORS.md
django_datadog_logger-0.7.3.dist-info/LICENSE
django_datadog_logger-0.7.3.dist-info/METADATA
django_datadog_logger-0.7.3.dist-info/WHEEL
django_datadog_logger-0.7.3.dist-info/top_level.txt
django_datadog_logger-0.7.3.dist-info/RECORD
