Metadata-Version: 2.1
Name: django-datadog-logger
Version: 0.7.3
Summary: Django DataDog Logger integration package.
Home-page: https://github.com/namespace-ee/django-datadog-logger
Author: Lenno Nagel
Author-email: lenno@namespace.ee
License: MIT license
Keywords: django_datadog_logger
Classifier: Development Status :: 2 - Pre-Alpha
Classifier: Intended Audience :: Developers
Classifier: License :: OSI Approved :: MIT License
Classifier: Natural Language :: English
Classifier: Programming Language :: Python :: 3
Classifier: Programming Language :: Python :: 3.7
Classifier: Programming Language :: Python :: 3.8
Classifier: Programming Language :: Python :: 3.9
Classifier: Programming Language :: Python :: 3.10
Classifier: Programming Language :: Python :: 3.11
Classifier: Programming Language :: Python :: 3.12
Requires-Python: >=3.7
License-File: LICENSE
License-File: AUTHORS.md
Requires-Dist: JSON-log-formatter
Requires-Dist: Django
Requires-Dist: djangorestframework
Requires-Dist: backports.zoneinfo; python_version < "3.9"
